aura/__init__.py
aura/core.py
aura/feature_extractor.py
aura/graph_generator.py
aura/gui.py
aura/qa_engine.py
aura/vision_text_bridge.py
aura/vision_text_bridge_loader.py
aura_viz-1.0.1.dist-info/METADATA
aura_viz-1.0.1.dist-info/WHEEL
aura_viz-1.0.1.dist-info/top_level.txt
aura_viz-1.0.1.dist-info/RECORD
