Metadata-Version: 2.4
Name: aura-viz
Version: 1.0.1
Summary: AURA - Artificial Understanding & Reasoning Assistant
Home-page: https://github.com/hanish9193/AURA
Author: Hanish
Author-email: hanish.kumar9193@gmail.com
Keywords: data-visualization ai insights correlation analysis
Classifier: Development Status :: 4 - Beta
Classifier: Intended Audience :: Developers
Classifier: Intended Audience :: Science/Research
Classifier: License :: OSI Approved :: MIT License
Classifier: Programming Language :: Python :: 3
Classifier: Programming Language :: Python :: 3.8
Classifier: Programming Language :: Python :: 3.9
Classifier: Programming Language :: Python :: 3.10
Classifier: Programming Language :: Python :: 3.11
Classifier: Topic :: Scientific/Engineering :: Visualization
Classifier: Topic :: Scientific/Engineering :: Information Analysis
Requires-Python: >=3.8
Requires-Dist: pandas>=1.3.0
Requires-Dist: numpy>=1.20.0
Requires-Dist: matplotlib>=3.4.0
Requires-Dist: seaborn>=0.11.0
Requires-Dist: scikit-learn>=0.24.0
Requires-Dist: pillow>=8.0.0
Requires-Dist: tensorflow>=2.6.0
Requires-Dist: tqdm>=4.65.0
Requires-Dist: openai>=1.0.0
Requires-Dist: requests>=2.25.0
Dynamic: author
Dynamic: author-email
Dynamic: classifier
Dynamic: description
Dynamic: description-content-type
Dynamic: home-page
Dynamic: keywords
Dynamic: requires-dist
Dynamic: requires-python
Dynamic: summary
